MANIFEST.in
README.md
setup.py
Adafruit_DHT/Beaglebone_Black.py
Adafruit_DHT/Raspberry_Pi.py
Adafruit_DHT/Raspberry_Pi_2.py
Adafruit_DHT/Test.py
Adafruit_DHT/__init__.py
Adafruit_DHT/common.py
Adafruit_DHT/platform_detect.py
Adafruit_DHT_test.egg-info/PKG-INFO
Adafruit_DHT_test.egg-info/SOURCES.txt
Adafruit_DHT_test.egg-info/dependency_links.txt
Adafruit_DHT_test.egg-info/top_level.txt
source/_Beaglebone_Black_Driver.c
source/_Raspberry_Pi_2_Driver.c
source/_Raspberry_Pi_Driver.c
source/_Test_Driver.c
source/common_dht_read.c
source/common_dht_read.h
source/Beaglebone_Black/bbb_dht_read.c
source/Beaglebone_Black/bbb_dht_read.h
source/Beaglebone_Black/bbb_mmio.c
source/Beaglebone_Black/bbb_mmio.h
source/Raspberry_Pi/pi_dht_read.c
source/Raspberry_Pi/pi_dht_read.h
source/Raspberry_Pi/pi_mmio.c
source/Raspberry_Pi/pi_mmio.h
source/Raspberry_Pi_2/pi_2_dht_read.c
source/Raspberry_Pi_2/pi_2_dht_read.h
source/Raspberry_Pi_2/pi_2_mmio.c
source/Raspberry_Pi_2/pi_2_mmio.h
source/Test/test_dht_read.c
source/Test/test_dht_read.h