Metadata-Version: 1.1
Name: Adafruit-DHT-test
Version: 1.3.2
Summary: Library to get readings from the DHT11, DHT22, and AM2302 humidity and temperature sensors on a Raspberry Pi or Beaglebone Black.
Home-page: https://github.com/adafruit/Adafruit_Python_DHT/
Author: Tony DiCola
Author-email: tdicola@adafruit.com
License: MIT
Platform: UNKNOWN
Classifier: Development Status :: 4 - Beta
Classifier: Operating System :: POSIX :: Linux
Classifier: License :: OSI Approved :: MIT License
Classifier: Intended Audience :: Developers
Classifier: Programming Language :: Python :: 2.7
Classifier: Programming Language :: Python :: 3
Classifier: Topic :: Software Development
Classifier: Topic :: System :: Hardware
